lite_term_system_stats/__init__.py
lite_term_system_stats/__main__.py
lite_term_system_stats-0.2.1.dist-info/WHEEL
lite_term_system_stats-0.2.1.dist-info/METADATA
lite_term_system_stats-0.2.1.dist-info/RECORD
