Metadata-Version: 2.1
Name: lite-term-system-stats
Version: 0.2.1
Summary: 
Requires-Python: >=3.7,<4.0
Classifier: Programming Language :: Python :: 3
Classifier: Programming Language :: Python :: 3.10
Classifier: Programming Language :: Python :: 3.7
Classifier: Programming Language :: Python :: 3.8
Classifier: Programming Language :: Python :: 3.9
Requires-Dist: colorama (>=0.4.5,<0.5.0)
Requires-Dist: psutil (>=5.9.1,<6.0.0)
